core/__init__.py
core/deep_cfr.py
core/model.py
opponent_modeling/__init__.py
opponent_modeling/deep_cfr_with_opponent_modeling.py
opponent_modeling/opponent_model.py
training/__init__.py
training/train.py
training/train_mixed_with_opponent_modeling.py
training/train_with_opponent_modeling.py
utils/__init__.py
utils/logging.py
utils/settings.py
deepcfr_poker-0.3.0.dist-info/LICENSE.txt
deepcfr_poker-0.3.0.dist-info/METADATA
deepcfr_poker-0.3.0.dist-info/WHEEL
deepcfr_poker-0.3.0.dist-info/entry_points.txt
deepcfr_poker-0.3.0.dist-info/top_level.txt
deepcfr_poker-0.3.0.dist-info/RECORD
